openai_proxy/__init__.py
openai_proxy/app.py
openai_proxy/client.py
openai_proxy/code_blocks_parser/__init__.py
openai_proxy/code_blocks_parser/parser.py
openai_proxy/exception_handler.py
openai_proxy/helpers.py
openai_proxy/proxy_client.py
openai_proxy/routers.py
openai_proxy/schemas.py
openai_proxy/services/__init__.py
openai_proxy/services/openai_service.py
openai_proxy/settings/__init__.py
openai_proxy/settings/env_settings.py
openai_proxy/settings/openai_settings.py
openai_proxy/settings/proxy_client_settings.py
openai_proxy/tool_call_client/__init__.py
openai_proxy/tool_call_client/client.py
openai_proxy/tool_call_client/models.py
openai_async_functions-0.3.0.dist-info/LICENSE
openai_async_functions-0.3.0.dist-info/METADATA
openai_async_functions-0.3.0.dist-info/WHEEL
openai_async_functions-0.3.0.dist-info/RECORD
