Metadata-Version: 2.1
Name: openai-async-functions
Version: 0.3.0
Summary: 
License: MIT
Author: sigma inc.
Requires-Python: >=3.12,<3.13
Classifier: License :: OSI Approved :: MIT License
Classifier: Programming Language :: Python :: 3
Classifier: Programming Language :: Python :: 3.12
Requires-Dist: aiohttp (>=3.12.0,<4.0.0)
Requires-Dist: fastapi (>=0.115.11,<0.116.0)
Requires-Dist: httpx (>=0.28.1,<0.29.0)
Requires-Dist: jinja2 (>=3.1.6,<4.0.0)
Requires-Dist: loguru (>=0.7.3,<0.8.0)
Requires-Dist: openai (>=1.75.0,<2.0.0)
Requires-Dist: pydantic (>=2.11.2,<3.0.0)
Requires-Dist: pydantic-settings (>=2.8.1,<3.0.0)
Requires-Dist: uvicorn (>=0.34.0,<0.35.0)
